flask_board/__init__.py
flask_board/commands.py
flask_board/generator.py
flask_board/templates/__init__.py
flask_board/templates/jinja2/celery/.dockerignore
flask_board/templates/jinja2/celery/.env
flask_board/templates/jinja2/celery/Dockerfile
flask_board/templates/jinja2/celery/README.md
flask_board/templates/jinja2/celery/requirements.txt
flask_board/templates/jinja2/celery/server.py
flask_board/templates/jinja2/celery/worker.py
flask_board/templates/jinja2/celery/app/__init__.py
flask_board/templates/jinja2/celery/app/application.py
flask_board/templates/jinja2/celery/app/blueprints.py
flask_board/templates/jinja2/celery/app/config.py
flask_board/templates/jinja2/celery/app/exceptions.py
flask_board/templates/jinja2/celery/app/tasks.py
flask_board/templates/jinja2/celery/tests/__init__.py
flask_board/templates/jinja2/celery/tests/test_app.py
flask_board/templates/jinja2/default/.dockerignore
flask_board/templates/jinja2/default/.env
flask_board/templates/jinja2/default/Dockerfile
flask_board/templates/jinja2/default/README.md
flask_board/templates/jinja2/default/requirements.txt
flask_board/templates/jinja2/default/server.py
flask_board/templates/jinja2/default/app/__init__.py
flask_board/templates/jinja2/default/app/application.py
flask_board/templates/jinja2/default/app/blueprints.py
flask_board/templates/jinja2/default/app/config.py
flask_board/templates/jinja2/default/app/exceptions.py
flask_board/templates/jinja2/default/tests/__init__.py
flask_board/templates/jinja2/default/tests/test_app.py
flask_board/templates/jinja2/restful/.dockerignore
flask_board/templates/jinja2/restful/.env
flask_board/templates/jinja2/restful/Dockerfile
flask_board/templates/jinja2/restful/README.md
flask_board/templates/jinja2/restful/requirements.txt
flask_board/templates/jinja2/restful/server.py
flask_board/templates/jinja2/restful/app/__init__.py
flask_board/templates/jinja2/restful/app/application.py
flask_board/templates/jinja2/restful/app/blueprints.py
Flask_Board-0.2.2.dist-info/METADATA
Flask_Board-0.2.2.dist-info/WHEEL
Flask_Board-0.2.2.dist-info/entry_points.txt
Flask_Board-0.2.2.dist-info/top_level.txt
Flask_Board-0.2.2.dist-info/RECORD
