Metadata-Version: 2.1
Name: Flask-Board
Version: 0.2.2
Summary: Build base flask app depends on template.
Home-page: https://github.com/wwtg99/flask-board
Author: Wu Wentao
Author-email: wwtg99@gmail.com
License: MIT
Keywords: flask template
Platform: any
Classifier: Environment :: Console
Classifier: Intended Audience :: Developers
Classifier: Intended Audience :: Customer Service
Classifier: Intended Audience :: System Administrators
Classifier: License :: OSI Approved :: MIT License
Classifier: Operating System :: OS Independent
Classifier: Programming Language :: Python
Classifier: Programming Language :: Python :: 3
Classifier: Topic :: Software Development
Classifier: Topic :: Software Development :: Build Tools
Classifier: Topic :: Software Development :: Debuggers
Classifier: Topic :: Software Development :: Libraries
Classifier: Topic :: Software Development :: Libraries :: Python Modules
Classifier: Topic :: Utilities
Requires-Dist: Werkzeug (>=0.15)
Requires-Dist: Jinja2 (>=2.10.1)
Requires-Dist: flask (>=1.0)
Requires-Dist: click (>=5.1)
Requires-Dist: python-dotenv (>=0.12)
